OTSO/Callibrate.py
OTSO/Cone.py
OTSO/Coordtrans.py
OTSO/Cutoff.py
OTSO/Flight.py
OTSO/Magfield.py
OTSO/OTSO.py
OTSO/Planet.py
OTSO/Trace.py
OTSO/Trajectory.py
OTSO/__init__.py
OTSO/Parameters/__init__.py
OTSO/Parameters/functions/Extract.py
OTSO/Parameters/functions/Gvalues.py
OTSO/Parameters/functions/MHDinit.py
OTSO/Parameters/functions/MiddleMan.cp312-win_amd64.pyd
OTSO/Parameters/functions/MiddleMan.cpython-312-aarch64-linux-gnu.so
OTSO/Parameters/functions/MiddleMan.cpython-312-darwin.so
OTSO/Parameters/functions/MiddleMan.cpython-312-x86_64-linux-gnu.so
OTSO/Parameters/functions/OmniPull.py
OTSO/Parameters/functions/Parameters.par
OTSO/Parameters/functions/Request.py
OTSO/Parameters/functions/Server.py
OTSO/Parameters/functions/StationList.csv
OTSO/Parameters/functions/TSY01_Constants.py
OTSO/Parameters/functions/__init__.py
OTSO/Parameters/functions/cone_inputs.py
OTSO/Parameters/functions/cores.py
OTSO/Parameters/functions/cutoff_inputs.py
OTSO/Parameters/functions/date.py
OTSO/Parameters/functions/flight_inputs.py
OTSO/Parameters/functions/fortran_calls.py
OTSO/Parameters/functions/magfield_inputs.py
OTSO/Parameters/functions/misc.py
OTSO/Parameters/functions/otso_cone.py
OTSO/Parameters/functions/otso_coordtrans.py
OTSO/Parameters/functions/otso_cutoff.py
OTSO/Parameters/functions/otso_flight.py
OTSO/Parameters/functions/otso_magfield.py
OTSO/Parameters/functions/otso_planet.py
OTSO/Parameters/functions/otso_trace.py
OTSO/Parameters/functions/otso_trajectory.py
OTSO/Parameters/functions/planet_inputs.py
OTSO/Parameters/functions/readme_generators.py
OTSO/Parameters/functions/solar_wind.py
OTSO/Parameters/functions/stations.py
OTSO/Parameters/functions/trace_inputs.py
OTSO/Parameters/functions/trajectory_inputs.py
OTSO/Parameters/functions/libs/libgfortran.5.dylib
OTSO/Parameters/functions/libs/libgfortran.so.5
OTSO/Parameters/functions/libs/libgfortran.so.5.0.0
otso-1.0.19.dist-info/licenses/LICENSE
otso-1.0.19.dist-info/METADATA
otso-1.0.19.dist-info/WHEEL
otso-1.0.19.dist-info/entry_points.txt
otso-1.0.19.dist-info/top_level.txt
otso-1.0.19.dist-info/RECORD
