Metadata-Version: 2.4
Name: OTSO
Version: 1.0.19
Summary: Geomagnetic Cutoff Computation Tool
Home-page: https://github.com/NLarsen15/OTSOpy
Author: Nicholas Larsen
Author-email: nlarsen1505@gmail.com
Classifier: Programming Language :: Python :: 3
Classifier: License :: OSI Approved :: MIT License
Classifier: Operating System :: OS Independent
Requires-Python: >=3.12, <3.13
License-File: LICENSE
Requires-Dist: psutil==7.0.0
Requires-Dist: numpy<2.3.0,>=2.2.0; python_version >= "3.10"
Requires-Dist: pandas<2.3.0,>=2.2.0; python_version >= "3.10"
Requires-Dist: requests==2.32.3; python_version >= "3.10"
Dynamic: author
Dynamic: author-email
Dynamic: classifier
Dynamic: description
Dynamic: description-content-type
Dynamic: home-page
Dynamic: license-file
Dynamic: provides-extra
Dynamic: requires-dist
Dynamic: requires-python
Dynamic: summary
